[{"schoolID": 1473, "classID": 1, "scores": {"Toan": 1.1, "Li": 8.25, "Hoa": 8.97, "Van": 9.89, "Su": 8.11, "Dia": 7.38, "Anh": 3.49, "CN": 0.42, "CD": 5.43, "Tin": 2.04, "Sinh": 3.37}, "rank": "Yeu"}, {"schoolID": 1474, "classID": 2, "scores": {"Toan": 8.14, "Li": 4.65, "Hoa": 4.5, "Van": 8.63, "Su": 7.78, "Dia": 4.97, "Anh": 8.7, "CN": 7.98, "CD": 8.01, "Tin": 0.14, "Sinh": 7.78}, "rank": "Yeu"}, {"schoolID": 1475, "classID": 3, "scores": {"Toan": 5.48, "Li": 5.72, "Hoa": 7.81, "Van": 6.72, "Su": 7.36, "Dia": 2.93, "Anh": 6.5, "CN": 7.53, "CD": 6.52, "Tin": 1.6, "Sinh": 8.37}, "rank": "Yeu"}, {"schoolID": 1476, "classID": 4, "scores": {"Toan": 8.07, "Li": 6.38, "Hoa": 7.45, "Van": 3.15, "Su": 5.7, "Dia": 3.33, "Anh": 1.72, "CN": 0.5, "CD": 4.13, "Tin": 8.68, "Sinh": 1.9}, "rank": "Yeu"}, {"schoolID": 1477, "classID": 5, "scores": {"Toan": 9.65, "Li": 4.36, "Hoa": 4.09, "Van": 1.86, "Su": 9.96, "Dia": 4.64, "Anh": 6.85, "CN": 8.78, "CD": 9.17, "Tin": 0.44, "Sinh": 4.49}, "rank": "Yeu"}, {"schoolID": 1478, "classID": 6, "scores": {"Toan": 8.47, "Li": 2.25, "Hoa": 2.44, "Van": 7.8, "Su": 4.13, "Dia": 8.22, "Anh": 5.21, "CN": 0.45, "CD": 2.13, "Tin": 1.22, "Sinh": 2.9}, "rank": "Yeu"}, {"schoolID": 1479, "classID": 7, "scores": {"Toan": 5.38, "Li": 3.57, "Hoa": 0.57, "Van": 3.16, "Su": 2.55, "Dia": 5.91, "Anh": 3.91, "CN": 6.13, "CD": 9.33, "Tin": 6.51, "Sinh": 5.92}, "rank": "Yeu"}, {"schoolID": 1480, "classID": 8, "scores": {"Toan": 9.89, "Li": 2.35, "Hoa": 5.47, "Van": 0.63, "Su": 1.9, "Dia": 6.89, "Anh": 6.18, "CN": 5.82, "CD": 1.96, "Tin": 7.34, "Sinh": 1.46}, "rank": "Yeu"}, {"schoolID": 1481, "classID": 9, "scores": {"Toan": 3.65, "Li": 8.27, "Hoa": 2.15, "Van": 0.33, "Su": 2.25, "Dia": 6.19, "Anh": 2.4, "CN": 2.8, "CD": 6.04, "Tin": 7.59, "Sinh": 5.14}, "rank": "Yeu"}, {"schoolID": 1482, "classID": 10, "scores": {"Toan": 3.84, "Li": 6.93, "Hoa": 4.71, "Van": 0.1, "Su": 6.87, "Dia": 1.2, "Anh": 9.97, "CN": 8.32, "CD": 1.05, "Tin": 5.84, "Sinh": 0.73}, "rank": "Yeu"}, {"schoolID": 1483, "classID": 11, "scores": {"Toan": 8.51, "Li": 7.57, "Hoa": 1.05, "Van": 2.41, "Su": 6.45, "Dia": 7.65, "Anh": 9.64, "CN": 8.14, "CD": 6.43, "Tin": 4.2, "Sinh": 8.82}, "rank": "Yeu"}, {"schoolID": 1484, "classID": 12, "scores": {"Toan": 5.74, "Li": 0.75, "Hoa": 3.77, "Van": 8.24, "Su": 2.75, "Dia": 6.17, "Anh": 0.33, "CN": 0.46, "CD": 6.21, "Tin": 2.91, "Sinh": 5.96}, "rank": "Yeu"}, {"schoolID": 1485, "classID": 13, "scores": {"Toan": 9.69, "Li": 6.66, "Hoa": 0.93, "Van": 0.77, "Su": 0.61, "Dia": 1.83, "Anh": 8.49, "CN": 1.68, "CD": 3.92, "Tin": 8.74, "Sinh": 6.44}, "rank": "Yeu"}, {"schoolID": 1486, "classID": 14, "scores": {"Toan": 4.2, "Li": 0.61, "Hoa": 1.29, "Van": 0.43, "Su": 7.39, "Dia": 7.9, "Anh": 4.91, "CN": 7.73, "CD": 0.4, "Tin": 5.24, "Sinh": 0.48}, "rank": "Yeu"}, {"schoolID": 1487, "classID": 15, "scores": {"Toan": 6.46, "Li": 0.34, "Hoa": 0.85, "Van": 1.25, "Su": 5.58, "Dia": 0.67, "Anh": 0.85, "CN": 8.99, "CD": 6.22, "Tin": 2.26, "Sinh": 7.58}, "rank": "Yeu"}, {"schoolID": 1488, "classID": 16, "scores": {"Toan": 3.79, "Li": 9.39, "Hoa": 5.57, "Van": 8.95, "Su": 9.81, "Dia": 6.89, "Anh": 9.16, "CN": 0.69, "CD": 9.3, "Tin": 6.55, "Sinh": 5.49}, "rank": "Yeu"}, {"schoolID": 1489, "classID": 17, "scores": {"Toan": 9.48, "Li": 2.5, "Hoa": 9.78, "Van": 0.68, "Su": 1.76, "Dia": 5.42, "Anh": 4.41, "CN": 6.01, "CD": 0.97, "Tin": 0.72, "Sinh": 7.99}, "rank": "Yeu"}, {"schoolID": 1490, "classID": 18, "scores": {"Toan": 9.4, "Li": 1.84, "Hoa": 8.59, "Van": 4.65, "Su": 4.5, "Dia": 2.99, "Anh": 0.69, "CN": 2.14, "CD": 2.62, "Tin": 4.77, "Sinh": 7.58}, "rank": "Yeu"}, {"schoolID": 1491, "classID": 19, "scores": {"Toan": 8.09, "Li": 6.23, "Hoa": 0.4, "Van": 0.88, "Su": 5.05, "Dia": 6.86, "Anh": 3.94, "CN": 9.06, "CD": 2.51, "Tin": 3.98, "Sinh": 5.32}, "rank": "Yeu"}, {"schoolID": 1492, "classID": 20, "scores": {"Toan": 2.22, "Li": 2.95, "Hoa": 5.34, "Van": 5.58, "Su": 5.68, "Dia": 8.09, "Anh": 7.69, "CN": 1.26, "CD": 1.94, "Tin": 6.87, "Sinh": 1.22}, "rank": "Yeu"}, {"schoolID": 1493, "classID": 21, "scores": {"Toan": 4.25, "Li": 8.33, "Hoa": 5.54, "Van": 0.89, "Su": 0.57, "Dia": 3.05, "Anh": 2.15, "CN": 3.66, "CD": 6.17, "Tin": 3.8, "Sinh": 4.29}, "rank": "Yeu"}, {"schoolID": 1494, "classID": 22, "scores": {"Toan": 8.44, "Li": 7.94, "Hoa": 4.02, "Van": 4.59, "Su": 3.74, "Dia": 4.52, "Anh": 3.48, "CN": 6.91, "CD": 7.78, "Tin": 3.56, "Sinh": 1.47}, "rank": "Yeu"}, {"schoolID": 1495, "classID": 23, "scores": {"Toan": 3.24, "Li": 5.27, "Hoa": 3.93, "Van": 7.66, "Su": 1.74, "Dia": 1.6, "Anh": 9.2, "CN": 8.54, "CD": 1.11, "Tin": 0.39, "Sinh": 0.63}, "rank": "Yeu"}, {"schoolID": 1496, "classID": 24, "scores": {"Toan": 7.66, "Li": 7.53, "Hoa": 4.02, "Van": 7.7, "Su": 2.55, "Dia": 7.57, "Anh": 9.92, "CN": 5.89, "CD": 6.57, "Tin": 6.57, "Sinh": 8.75}, "rank": "Yeu"}, {"schoolID": 1497, "classID": 25, "scores": {"Toan": 2.68, "Li": 0.26, "Hoa": 1.44, "Van": 4.03, "Su": 6.06, "Dia": 7.2, "Anh": 5.95, "CN": 6.4, "CD": 0.18, "Tin": 1.41, "Sinh": 4.23}, "rank": "Yeu"}, {"schoolID": 1498, "classID": 26, "scores": {"Toan": 5.07, "Li": 8.51, "Hoa": 9.11, "Van": 3.58, "Su": 9.16, "Dia": 8.99, "Anh": 2.54, "CN": 2.16, "CD": 3.08, "Tin": 5.61, "Sinh": 9.47}, "rank": "Yeu"}, {"schoolID": 1499, "classID": 27, "scores": {"Toan": 3.41, "Li": 9.32, "Hoa": 2.4, "Van": 4.54, "Su": 5.86, "Dia": 5.0, "Anh": 4.76, "CN": 6.09, "CD": 2.86, "Tin": 8.2, "Sinh": 7.78}, "rank": "Yeu"}, {"schoolID": 1500, "classID": 28, "scores": {"Toan": 6.15, "Li": 0.65, "Hoa": 9.23, "Van": 4.78, "Su": 7.09, "Dia": 4.76, "Anh": 6.2, "CN": 5.58, "CD": 4.83, "Tin": 7.37, "Sinh": 6.08}, "rank": "Yeu"}, {"schoolID": 1501, "classID": 29, "scores": {"Toan": 2.59, "Li": 8.12, "Hoa": 0.15, "Van": 4.09, "Su": 6.31, "Dia": 1.07, "Anh": 8.9, "CN": 3.62, "CD": 3.56, "Tin": 8.29, "Sinh": 0.95}, "rank": "Yeu"}, {"schoolID": 1502, "classID": 30, "scores": {"Toan": 5.18, "Li": 0.65, "Hoa": 5.08, "Van": 2.81, "Su": 0.31, "Dia": 3.77, "Anh": 0.04, "CN": 5.2, "CD": 1.33, "Tin": 0.7, "Sinh": 6.86}, "rank": "Yeu"}]